liesel/__init__.py
liesel/__version__.py
liesel/docs.py
liesel/logging.py
liesel/option.py
liesel/py.typed
liesel/bijectors/__init__.py
liesel/bijectors/algebraic_sigmoid.py
liesel/contrib/__init__.py
liesel/contrib/splines.py
liesel/distributions/__init__.py
liesel/distributions/copulas.py
liesel/distributions/mvn_degen.py
liesel/distributions/nodist.py
liesel/experimental/__init__.py
liesel/experimental/arviz.py
liesel/experimental/pymc.py
liesel/goose/__init__.py
liesel/goose/builder.py
liesel/goose/chain.py
liesel/goose/da.py
liesel/goose/engine.py
liesel/goose/epoch.py
liesel/goose/gibbs.py
liesel/goose/hmc.py
liesel/goose/interface.py
liesel/goose/iwls.py
liesel/goose/iwls_utils.py
liesel/goose/kernel.py
liesel/goose/kernel_sequence.py
liesel/goose/mcmc_spec.py
liesel/goose/mh.py
liesel/goose/mh_kernel.py
liesel/goose/mm.py
liesel/goose/nuts.py
liesel/goose/optim.py
liesel/goose/pytree.py
liesel/goose/rw.py
liesel/goose/summary_m.py
liesel/goose/summary_viz.py
liesel/goose/types.py
liesel/goose/warmup.py
liesel/model/__init__.py
liesel/model/distreg.py
liesel/model/goose.py
liesel/model/legacy.py
liesel/model/model.py
liesel/model/nodes.py
liesel/model/viz.py
liesel-0.4.4.dist-info/METADATA
liesel-0.4.4.dist-info/WHEEL
liesel-0.4.4.dist-info/licenses/LICENSE.md
liesel-0.4.4.dist-info/RECORD
