Metadata-Version: 2.4
Name: liesel
Version: 0.4.4
Summary: A probabilistic programming framework with a focus on semi-parametric regression
Project-URL: Homepage, https://liesel-project.org
Project-URL: Documentation, https://liesel-project.org
Project-URL: Repository, https://github.com/liesel-devs/liesel.git
Author: Paul Wiemann, Hannes Riebl, Johannes Brachem, Gianmarco Callegher
License-Expression: MIT
License-File: LICENSE.md
Keywords: machine-learning,statistics
Classifier: Intended Audience :: Science/Research
Classifier: License :: OSI Approved :: MIT License
Classifier: Programming Language :: Python :: 3
Classifier: Programming Language :: Python :: 3.13
Requires-Python: <3.14,>=3.13
Requires-Dist: arviz>=0.15
Requires-Dist: blackjax>=1.0
Requires-Dist: dill>=0.3
Requires-Dist: jax>=0.5.0
Requires-Dist: jaxlib>=0.5.0
Requires-Dist: matplotlib>=3.5
Requires-Dist: networkx>=3.4.2
Requires-Dist: numpy>=2.0
Requires-Dist: optax>=0.1.7
Requires-Dist: pandas>=1.4
Requires-Dist: pydot>=3.0
Requires-Dist: scipy>=1.8.0
Requires-Dist: seaborn>=0.13
Requires-Dist: tfp-nightly>=0.26.0.dev20250811
Requires-Dist: tqdm>=4.62
